pyCommonTools.py
pyCommonTools-2.3.0.dist-info/LICENSE
pyCommonTools-2.3.0.dist-info/METADATA
pyCommonTools-2.3.0.dist-info/WHEEL
pyCommonTools-2.3.0.dist-info/top_level.txt
pyCommonTools-2.3.0.dist-info/RECORD
