Metadata-Version: 2.1
Name: pyCommonTools
Version: 2.3.0
Summary: Module of commonly used functions, classes and tools for research
Requires-Dist: pytest
